[
  {
    "title": "Como Planejar uma Reforma de Cozinha Completa: Guia Definitivo",
    "date": "2024-04-15T09:00:00Z",
    "slug": "como-planejar-uma-reforma-de-cozinha-completa",
    "featured": true,
    "tags": [
      "reforma",
      "cozinha",
      "planejamento",
      "orçamento",
      "dicas"
    ],
    "category": "reformas-residenciais"
  },
  {
    "title": "Descubra as 5 Maiores Tendências de Design de Interiores para 2022 - Repagine Sua Casa!",
    "date": "2022-04-08T22:31:35.891Z",
    "slug": "descubra-as-5-maiores-tendencias-de-design-de-interiores-para-2022-repagine-sua-casa",
    "featured": false,
    "tags": [
      "reformas",
      "dicas",
      "casa"
    ],
    "category": "tendencias"
  }
]